elpee/__init__.py
elpee/algorithms/__init__.py
elpee/algorithms/all_stack_starter.py
elpee/algorithms/big_m.py
elpee/algorithms/dual_simplex.py
elpee/alternator.py
elpee/datahandler/__init__.py
elpee/datahandler/data_handler.py
elpee/datahandler/json_handler.py
elpee/datahandler/yaml_handler.py
elpee/elpee_solver.py
elpee/utils/__init__.py
elpee/utils/configs.py
elpee/utils/configs.yaml
elpee/utils/feasible.py
elpee/utils/printer.py
elpee/utils/protocols/__init__.py
elpee/utils/protocols/handler.py
elpee/utils/protocols/lp_problem.py
elpee/utils/protocols/st_problem.py
elpee/utils/utilities.py
elpee-1.0.3.dist-info/LICENSE
elpee-1.0.3.dist-info/METADATA
elpee-1.0.3.dist-info/NOTICE
elpee-1.0.3.dist-info/WHEEL
elpee-1.0.3.dist-info/RECORD
