Metadata-Version: 2.1
Name: elpee
Version: 1.0.3
Summary: Solving linear programming problems step-by-step
Home-page: https://github.com/navindu-ds/elpee
License: Apache-2.0
Keywords: optimization,linear programming,operational research
Author: Navindu De Silva
Author-email: navinduydds@gmail.com 
Requires-Python: >=3.9,<4.0
Classifier: License :: OSI Approved :: Apache Software License
Classifier: Programming Language :: Python :: 3
Classifier: Programming Language :: Python :: 3.9
Classifier: Programming Language :: Python :: 3.10
Classifier: Programming Language :: Python :: 3.11
Classifier: Programming Language :: Python :: 3.12
Requires-Dist: pyyaml (>=6.0.1,<7.0.0)
Requires-Dist: sympy (>=1.12.1,<2.0.0)
Project-URL: Documentation, https://elpee.readthedocs.io/
Project-URL: Repository, https://github.com/navindu-ds/elpee
